gmpy2-2.2.1.dist-info/COPYING
gmpy2-2.2.1.dist-info/COPYING.LESSER
gmpy2-2.2.1.dist-info/WHEEL
gmpy2-2.2.1.dist-info/top_level.txt
gmpy2-2.2.1.dist-info/RECORD
gmpy2-2.2.1.dist-info/METADATA
gmpy2/gmpy2.h
gmpy2/gmp.h
gmpy2/__init__.py
gmpy2/mpc.h
gmpy2/mpfr.h
gmpy2/__init__.pxd
gmpy2/gmpy2.pxd
gmpy2/gmpy2.cpython-310-i386-linux-gnu.so
gmpy2.libs/libgmp-9b7bdac1.so.10.5.0
gmpy2.libs/libmpfr-2ca02d32.so.6.2.1
gmpy2.libs/libmpc-0ebcdf52.so.3.3.1
